colorflow/__init__.py
colorflow/core/color.py
colorflow/core/sequence.py
colorflow/enum.py
colorflow/parser/color_parser.py
colorflow/utils/color_presets.py
colorflow/utils/mapper.py
colorflow-2.0.0.dist-info/LICENSE
colorflow-2.0.0.dist-info/METADATA
colorflow-2.0.0.dist-info/WHEEL
colorflow-2.0.0.dist-info/RECORD
