Metadata-Version: 2.1
Name: ColorFlow
Version: 2.0.0
Summary: A Python library for creating and applying full-color, linear, and circular gradients to text with easy color management.
License: MIT
Keywords: python,color,flow,easy,cmd,app,manage,text,colour,ansi,terminal
Author: Pcoi94
Requires-Python: >=3.6
Classifier: Intended Audience :: Developers
Classifier: License :: OSI Approved :: MIT License
Classifier: Operating System :: MacOS :: MacOS X
Classifier: Operating System :: Microsoft :: Windows
Classifier: Operating System :: Unix
Classifier: Programming Language :: Python :: 3
Classifier: Programming Language :: Python :: 3.6
Classifier: Programming Language :: Python :: 3.7
Classifier: Programming Language :: Python :: 3.8
Classifier: Programming Language :: Python :: 3.9
Classifier: Programming Language :: Python :: 3.10
Classifier: Programming Language :: Python :: 3.11
Classifier: Programming Language :: Python :: 3.12
Classifier: Programming Language :: Python :: 3.13
Requires-Dist: dataclasses (>=0.6)
Requires-Dist: typing (>=3.7.4.3)
